{
    "nodes": [
        {
            "num": "A00"
        },
        {
            "num": "A30"
        },
        {
            "num": "A25"
        },
        {
            "num": "A47"
        },
        {
            "num": "A08"
        },
        {
            "num": "A13"
        },
        {
            "num": "A01"
        },
        {
            "num": "A21"
        },
        {
            "num": "A19"
        },
        {
            "num": "A02"
        },
        {
            "num": "A05"
        },
        {
            "num": "J48"
        },
        {
            "num": "J51"
        },
        {
            "num": "A28"
        },
        {
            "num": "A10"
        },
        {
            "num": "A07"
        },
        {
            "num": "A12"
        },
        {
            "num": "F16"
        },
        {
            "num": "A22"
        },
        {
            "num": "J50"
        }
    ],
    "links": [
        {
            "source": 0,
            "target": 1,
            "property": [
                {
                    "tf": "FALSE",
                    "dur": "58000",
                    "stamp": "1394474",
                    "date": "3/10/2014",
                    "time": "4:41:14 AM"
                },
                {
                    "tf": "FALSE",
                    "dur": "23000",
                    "stamp": "1394705",
                    "date": "3/10/2014",
                    "time": "3:55:05 AM"
                },
                {
                    "tf": "FALSE",
                    "dur": "83000",
                    "stamp": "1390255",
                    "date": "1/23/2014",
                    "time": "12:00:55 AM"
                }
            ]
        },
        {
            "source": 1,
            "target": 2,
            "property": [
                {
                    "tf": "FALSE",
                    "dur": "40000",
                    "stamp": "1392938",
                    "date": "2/19/2014",
                    "time": "2:08:58 PM"
                },
                {
                    "tf": "FALSE",
                    "dur": "23000",
                    "stamp": "1392065",
                    "date": "2/19/2014",
                    "time": "10:01:05 AM"
                }
            ]
        },
        {
            "source": 1,
            "target": 3,
            "property": [
                {
                    "tf": "FALSE",
                    "dur": "19000",
                    "stamp": "1390742",
                    "date": "1/24/2014",
                    "time": "5:32:22 PM"
                }
            ]
        },
        {
            "source": 1,
            "target": 4,
            "property": [
                {
                    "tf": "FALSE",
                    "dur": "50000",
                    "stamp": "1394616",
                    "date": "3/10/2014",
                    "time": "3:20:16 AM"
                },
                {
                    "tf": "FALSE",
                    "dur": "21000",
                    "stamp": "1394178",
                    "date": "3/10/2014",
                    "time": "3:12:58 AM"
                },
                {
                    "tf": "FALSE",
                    "dur": "42000",
                    "stamp": "1394331",
                    "date": "3/10/2014",
                    "time": "2:58:51 AM"
                },
                {
                    "tf": "FALSE",
                    "dur": "25000",
                    "stamp": "1394101",
                    "date": "3/10/2014",
                    "time": "2:55:01 AM"
                },
                {
                    "tf": "FALSE",
                    "dur": "6000",
                    "stamp": "1394981",
                    "date": "3/7/2014",
                    "time": "6:49:41 AM"
                },
                {
                    "tf": "FALSE",
                    "dur": "7000",
                    "stamp": "1394052",
                    "date": "3/7/2014",
                    "time": "1:17:32 AM"
                },
                {
                    "tf": "FALSE",
                    "dur": "21000",
                    "stamp": "1394627",
                    "date": "3/6/2014",
                    "time": "4:53:47 AM"
                },
                {
                    "tf": "FALSE",
                    "dur": "4000",
                    "stamp": "1393483",
                    "date": "2/28/2014",
                    "time": "8:01:23 AM"
                },
                {
                    "tf": "FALSE",
                    "dur": "16000",
                    "stamp": "1393802",
                    "date": "2/27/2014",
                    "time": "6:16:42 AM"
                },
                {
                    "tf": "FALSE",
                    "dur": "32000",
                    "stamp": "1393938",
                    "date": "2/27/2014",
                    "time": "2:42:18 AM"
                },
                {
                    "tf": "FALSE",
                    "dur": "8000",
                    "stamp": "1392720",
                    "date": "2/18/2014",
                    "time": "9:28:40 AM"
                },
                {
                    "tf": "FALSE",
                    "dur": "8000",
                    "stamp": "1392199",
                    "date": "2/18/2014",
                    "time": "9:19:59 AM"
                },
                {
                    "tf": "FALSE",
                    "dur": "15000",
                    "stamp": "1392031",
                    "date": "2/11/2014",
                    "time": "5:53:51 AM"
                },
                {
                    "tf": "FALSE",
                    "dur": "53000",
                    "stamp": "1391988",
                    "date": "2/7/2014",
                    "time": "12:29:48 AM"
                },
                {
                    "tf": "FALSE",
                    "dur": "11000",
                    "stamp": "1391126",
                    "date": "2/6/2014",
                    "time": "11:58:46 PM"
                }
            ]
        },
        {
            "source": 1,
            "target": 5,
            "property": [
                {
                    "tf": "TRUE",
                    "dur": "27000",
                    "stamp": "1394242",
                    "date": "3/12/2014",
                    "time": "7:27:22 AM"
                }
            ]
        },
        {
            "source": 1,
            "target": 6,
            "property": [
                {
                    "tf": "TRUE",
                    "dur": "34000",
                    "stamp": "1394880",
                    "date": "3/12/2014",
                    "time": "6:31:20 AM"
                }
            ]
        },
        {
            "source": 1,
            "target": 7,
            "property": [
                {
                    "tf": "TRUE",
                    "dur": "-1",
                    "stamp": "1394811",
                    "date": "3/12/2014",
                    "time": "6:30:11 AM"
                }
            ]
        },
        {
            "source": 1,
            "target": 8,
            "property": [
                {
                    "tf": "TRUE",
                    "dur": "-1",
                    "stamp": "1394730",
                    "date": "3/12/2014",
                    "time": "6:28:50 AM"
                }
            ]
        },
        {
            "source": 1,
            "target": 6,
            "property": [
                {
                    "tf": "TRUE",
                    "dur": "-1",
                    "stamp": "1394172",
                    "date": "3/11/2014",
                    "time": "10:49:32 PM"
                },
                {
                    "tf": "TRUE",
                    "dur": "-1",
                    "stamp": "1394996",
                    "date": "3/11/2014",
                    "time": "10:46:36 PM"
                }
            ]
        },
        {
            "source": 1,
            "target": 9,
            "property": [
                {
                    "tf": "TRUE",
                    "dur": "-1",
                    "stamp": "1394937",
                    "date": "3/11/2014",
                    "time": "10:45:37 PM"
                }
            ]
        },
        {
            "source": 1,
            "target": 5,
            "property": [
                {
                    "tf": "TRUE",
                    "dur": "21000",
                    "stamp": "1394740",
                    "date": "3/11/2014",
                    "time": "9:35:40 PM"
                }
            ]
        },
        {
            "source": 1,
            "target": 10,
            "property": [
                {
                    "tf": "TRUE",
                    "dur": "14000",
                    "stamp": "1394082",
                    "date": "3/10/2014",
                    "time": "4:01:22 AM"
                },
                {
                    "tf": "TRUE",
                    "dur": "65000",
                    "stamp": "1394811",
                    "date": "3/10/2014",
                    "time": "3:56:51 AM"
                }
            ]
        },
        {
            "source": 1,
            "target": 5,
            "property": [
                {
                    "tf": "TRUE",
                    "dur": "-1",
                    "stamp": "1394745",
                    "date": "3/10/2014",
                    "time": "3:55:45 AM"
                }
            ]
        },
        {
            "source": 1,
            "target": 0,
            "property": [
                {
                    "tf": "TRUE",
                    "dur": "3000",
                    "stamp": "1394676",
                    "date": "3/10/2014",
                    "time": "3:54:36 AM"
                }
            ]
        },
        {
            "source": 1,
            "target": 11,
            "property": [
                {
                    "tf": "TRUE",
                    "dur": "-1",
                    "stamp": "1394609",
                    "date": "3/10/2014",
                    "time": "3:53:29 AM"
                },
                {
                    "tf": "TRUE",
                    "dur": "-1",
                    "stamp": "1394552",
                    "date": "3/10/2014",
                    "time": "3:52:32 AM"
                }
            ]
        },
        {
            "source": 1,
            "target": 5,
            "property": [
                {
                    "tf": "TRUE",
                    "dur": "-1",
                    "stamp": "1394288",
                    "date": "3/10/2014",
                    "time": "3:48:08 AM"
                }
            ]
        },
        {
            "source": 1,
            "target": 4,
            "property": [
                {
                    "tf": "TRUE",
                    "dur": "50000",
                    "stamp": "1394476",
                    "date": "3/10/2014",
                    "time": "3:17:56 AM"
                }
            ]
        },
        {
            "source": 1,
            "target": 12,
            "property": [
                {
                    "tf": "TRUE",
                    "dur": "82000",
                    "stamp": "1394351",
                    "date": "3/10/2014",
                    "time": "3:15:51 AM"
                }
            ]
        },
        {
            "source": 1,
            "target": 4,
            "property": [
                {
                    "tf": "TRUE",
                    "dur": "21000",
                    "stamp": "1394032",
                    "date": "3/10/2014",
                    "time": "3:10:32 AM"
                },
                {
                    "tf": "TRUE",
                    "dur": "42000",
                    "stamp": "1394192",
                    "date": "3/10/2014",
                    "time": "2:56:32 AM"
                },
                {
                    "tf": "TRUE",
                    "dur": "25000",
                    "stamp": "1394962",
                    "date": "3/10/2014",
                    "time": "2:52:42 AM"
                }
            ]
        },
        {
            "source": 1,
            "target": 13,
            "property": [
                {
                    "tf": "TRUE",
                    "dur": "38000",
                    "stamp": "1394611",
                    "date": "3/10/2014",
                    "time": "2:13:31 AM"
                }
            ]
        },
        {
            "source": 1,
            "target": 4,
            "property": [
                {
                    "tf": "TRUE",
                    "dur": "7000",
                    "stamp": "1394844",
                    "date": "3/7/2014",
                    "time": "6:47:24 AM"
                }
            ]
        },
        {
            "source": 1,
            "target": 14,
            "property": [
                {
                    "tf": "TRUE",
                    "dur": "47000",
                    "stamp": "1394106",
                    "date": "3/7/2014",
                    "time": "1:35:06 AM"
                }
            ]
        },
        {
            "source": 1,
            "target": 4,
            "property": [
                {
                    "tf": "TRUE",
                    "dur": "7000",
                    "stamp": "1394913",
                    "date": "3/7/2014",
                    "time": "1:15:13 AM"
                }
            ]
        },
        {
            "source": 1,
            "target": 15,
            "property": [
                {
                    "tf": "TRUE",
                    "dur": "11000",
                    "stamp": "1394982",
                    "date": "3/6/2014",
                    "time": "7:09:42 PM"
                }
            ]
        },
        {
            "source": 1,
            "target": 16,
            "property": [
                {
                    "tf": "TRUE",
                    "dur": "-1",
                    "stamp": "1394177",
                    "date": "3/6/2014",
                    "time": "9:46:17 AM"
                },
                {
                    "tf": "TRUE",
                    "dur": "-1",
                    "stamp": "1394153",
                    "date": "3/6/2014",
                    "time": "9:45:53 AM"
                }
            ]
        },
        {
            "source": 1,
            "target": 15,
            "property": [
                {
                    "tf": "TRUE",
                    "dur": "7000",
                    "stamp": "1394918",
                    "date": "3/6/2014",
                    "time": "5:31:58 AM"
                },
                {
                    "tf": "TRUE",
                    "dur": "22000",
                    "stamp": "1394157",
                    "date": "3/6/2014",
                    "time": "5:19:17 AM"
                }
            ]
        },
        {
            "source": 1,
            "target": 14,
            "property": [
                {
                    "tf": "TRUE",
                    "dur": "65000",
                    "stamp": "1394776",
                    "date": "3/6/2014",
                    "time": "4:56:16 AM"
                },
                {
                    "tf": "TRUE",
                    "dur": "92000",
                    "stamp": "1394594",
                    "date": "3/6/2014",
                    "time": "4:53:14 AM"
                }
            ]
        },
        {
            "source": 1,
            "target": 4,
            "property": [
                {
                    "tf": "TRUE",
                    "dur": "21000",
                    "stamp": "1394490",
                    "date": "3/6/2014",
                    "time": "4:51:30 AM"
                }
            ]
        },
        {
            "source": 1,
            "target": 17,
            "property": [
                {
                    "tf": "TRUE",
                    "dur": "41000",
                    "stamp": "1394082",
                    "date": "3/6/2014",
                    "time": "12:01:22 AM"
                }
            ]
        },
        {
            "source": 1,
            "target": 5,
            "property": [
                {
                    "tf": "TRUE",
                    "dur": "-1",
                    "stamp": "1394879",
                    "date": "3/5/2014",
                    "time": "11:57:59 PM"
                },
                {
                    "tf": "TRUE",
                    "dur": "-1",
                    "stamp": "1394834",
                    "date": "3/5/2014",
                    "time": "11:57:14 PM"
                }
            ]
        },
        {
            "source": 1,
            "target": 14,
            "property": [
                {
                    "tf": "TRUE",
                    "dur": "14000",
                    "stamp": "1393265",
                    "date": "3/3/2014",
                    "time": "4:34:25 AM"
                }
            ]
        },
        {
            "source": 1,
            "target": 15,
            "property": [
                {
                    "tf": "TRUE",
                    "dur": "-1",
                    "stamp": "1393240",
                    "date": "3/3/2014",
                    "time": "4:34:00 AM"
                }
            ]
        },
        {
            "source": 1,
            "target": 16,
            "property": [
                {
                    "tf": "TRUE",
                    "dur": "51000",
                    "stamp": "1393030",
                    "date": "3/2/2014",
                    "time": "9:17:10 PM"
                }
            ]
        },
        {
            "source": 1,
            "target": 10,
            "property": [
                {
                    "tf": "TRUE",
                    "dur": "6000",
                    "stamp": "1393306",
                    "date": "3/1/2014",
                    "time": "8:25:06 AM"
                }
            ]
        },
        {
            "source": 1,
            "target": 8,
            "property": [
                {
                    "tf": "TRUE",
                    "dur": "5000",
                    "stamp": "1393797",
                    "date": "3/1/2014",
                    "time": "7:26:37 AM"
                }
            ]
        },
        {
            "source": 1,
            "target": 4,
            "property": [
                {
                    "tf": "TRUE",
                    "dur": "6000",
                    "stamp": "1393350",
                    "date": "2/28/2014",
                    "time": "7:59:10 AM"
                },
                {
                    "tf": "TRUE",
                    "dur": "17000",
                    "stamp": "1393669",
                    "date": "2/27/2014",
                    "time": "6:14:29 AM"
                },
                {
                    "tf": "TRUE",
                    "dur": "32000",
                    "stamp": "1393804",
                    "date": "2/27/2014",
                    "time": "2:40:04 AM"
                }
            ]
        },
        {
            "source": 1,
            "target": 3,
            "property": [
                {
                    "tf": "TRUE",
                    "dur": "27000",
                    "stamp": "1393750",
                    "date": "2/27/2014",
                    "time": "2:39:10 AM"
                }
            ]
        },
        {
            "source": 1,
            "target": 10,
            "property": [
                {
                    "tf": "TRUE",
                    "dur": "-1",
                    "stamp": "1393500",
                    "date": "2/27/2014",
                    "time": "2:35:00 AM"
                }
            ]
        },
        {
            "source": 1,
            "target": 16,
            "property": [
                {
                    "tf": "TRUE",
                    "dur": "20000",
                    "stamp": "1393311",
                    "date": "2/27/2014",
                    "time": "12:01:51 AM"
                },
                {
                    "tf": "TRUE",
                    "dur": "17000",
                    "stamp": "1393179",
                    "date": "2/26/2014",
                    "time": "3:26:19 AM"
                }
            ]
        },
        {
            "source": 1,
            "target": 5,
            "property": [
                {
                    "tf": "TRUE",
                    "dur": "61000",
                    "stamp": "1393202",
                    "date": "2/25/2014",
                    "time": "5:46:42 AM"
                }
            ]
        },
        {
            "source": 1,
            "target": 18,
            "property": [
                {
                    "tf": "TRUE",
                    "dur": "27000",
                    "stamp": "1393564",
                    "date": "2/23/2014",
                    "time": "6:56:04 AM"
                }
            ]
        },
        {
            "source": 1,
            "target": 14,
            "property": [
                {
                    "tf": "TRUE",
                    "dur": "53000",
                    "stamp": "1393479",
                    "date": "2/23/2014",
                    "time": "6:54:39 AM"
                }
            ]
        },
        {
            "source": 1,
            "target": 15,
            "property": [
                {
                    "tf": "TRUE",
                    "dur": "-1",
                    "stamp": "1393417",
                    "date": "2/23/2014",
                    "time": "6:53:37 AM"
                }
            ]
        },
        {
            "source": 1,
            "target": 10,
            "property": [
                {
                    "tf": "TRUE",
                    "dur": "8000",
                    "stamp": "1393745",
                    "date": "2/22/2014",
                    "time": "6:49:05 AM"
                }
            ]
        },
        {
            "source": 1,
            "target": 6,
            "property": [
                {
                    "tf": "TRUE",
                    "dur": "50000",
                    "stamp": "1393595",
                    "date": "2/22/2014",
                    "time": "5:06:35 AM"
                }
            ]
        },
        {
            "source": 1,
            "target": 14,
            "property": [
                {
                    "tf": "TRUE",
                    "dur": "32000",
                    "stamp": "1393976",
                    "date": "2/21/2014",
                    "time": "11:56:16 PM"
                }
            ]
        },
        {
            "source": 1,
            "target": 18,
            "property": [
                {
                    "tf": "TRUE",
                    "dur": "-1",
                    "stamp": "1392864",
                    "date": "2/21/2014",
                    "time": "6:07:44 AM"
                },
                {
                    "tf": "TRUE",
                    "dur": "-1",
                    "stamp": "1392832",
                    "date": "2/21/2014",
                    "time": "6:07:12 AM"
                }
            ]
        },
        {
            "source": 1,
            "target": 19,
            "property": [
                {
                    "tf": "TRUE",
                    "dur": "15000",
                    "stamp": "1392408",
                    "date": "2/20/2014",
                    "time": "9:56:48 PM"
                }
            ]
        },
        {
            "source": 1,
            "target": 15,
            "property": [
                {
                    "tf": "TRUE",
                    "dur": "46000",
                    "stamp": "1392353",
                    "date": "2/19/2014",
                    "time": "2:49:13 PM"
                }
            ]
        },
        {
            "source": 1,
            "target": 2,
            "property": [
                {
                    "tf": "TRUE",
                    "dur": "40000",
                    "stamp": "1392934",
                    "date": "2/19/2014",
                    "time": "2:08:54 PM"
                },
                {
                    "tf": "TRUE",
                    "dur": "23000",
                    "stamp": "1392060",
                    "date": "2/19/2014",
                    "time": "10:01:00 AM"
                }
            ]
        },
        {
            "source": 1,
            "target": 4,
            "property": [
                {
                    "tf": "TRUE",
                    "dur": "9000",
                    "stamp": "1392594",
                    "date": "2/18/2014",
                    "time": "9:26:34 AM"
                },
                {
                    "tf": "TRUE",
                    "dur": "9000",
                    "stamp": "1392073",
                    "date": "2/18/2014",
                    "time": "9:17:53 AM"
                }
            ]
        },
        {
            "source": 1,
            "target": 5,
            "property": [
                {
                    "tf": "TRUE",
                    "dur": "-1",
                    "stamp": "1392168",
                    "date": "2/16/2014",
                    "time": "3:09:28 AM"
                },
                {
                    "tf": "TRUE",
                    "dur": "-1",
                    "stamp": "1392156",
                    "date": "2/16/2014",
                    "time": "3:09:16 AM"
                },
                {
                    "tf": "TRUE",
                    "dur": "-1",
                    "stamp": "1392446",
                    "date": "2/16/2014",
                    "time": "1:50:46 AM"
                },
                {
                    "tf": "TRUE",
                    "dur": "-1",
                    "stamp": "1392385",
                    "date": "2/16/2014",
                    "time": "1:49:45 AM"
                },
                {
                    "tf": "TRUE",
                    "dur": "-1",
                    "stamp": "1392370",
                    "date": "2/16/2014",
                    "time": "1:49:30 AM"
                }
            ]
        },
        {
            "source": 1,
            "target": 15,
            "property": [
                {
                    "tf": "TRUE",
                    "dur": "8000",
                    "stamp": "1392106",
                    "date": "2/15/2014",
                    "time": "8:15:06 AM"
                },
                {
                    "tf": "TRUE",
                    "dur": "21000",
                    "stamp": "1392969",
                    "date": "2/15/2014",
                    "time": "7:56:09 AM"
                },
                {
                    "tf": "TRUE",
                    "dur": "70000",
                    "stamp": "1392443",
                    "date": "2/15/2014",
                    "time": "7:14:03 AM"
                }
            ]
        },
        {
            "source": 1,
            "target": 5,
            "property": [
                {
                    "tf": "TRUE",
                    "dur": "34000",
                    "stamp": "1392347",
                    "date": "2/13/2014",
                    "time": "11:32:27 PM"
                }
            ]
        },
        {
            "source": 1,
            "target": 4,
            "property": [
                {
                    "tf": "TRUE",
                    "dur": "15000",
                    "stamp": "1392908",
                    "date": "2/11/2014",
                    "time": "5:51:48 AM"
                }
            ]
        },
        {
            "source": 1,
            "target": 15,
            "property": [
                {
                    "tf": "TRUE",
                    "dur": "-1",
                    "stamp": "1392372",
                    "date": "2/10/2014",
                    "time": "6:39:32 AM"
                }
            ]
        },
        {
            "source": 1,
            "target": 13,
            "property": [
                {
                    "tf": "TRUE",
                    "dur": "-1",
                    "stamp": "1392469",
                    "date": "2/10/2014",
                    "time": "5:51:09 AM"
                }
            ]
        },
        {
            "source": 1,
            "target": 10,
            "property": [
                {
                    "tf": "TRUE",
                    "dur": "-1",
                    "stamp": "1391595",
                    "date": "2/9/2014",
                    "time": "8:46:35 AM"
                },
                {
                    "tf": "TRUE",
                    "dur": "16000",
                    "stamp": "1391229",
                    "date": "2/9/2014",
                    "time": "8:40:29 AM"
                }
            ]
        },
        {
            "source": 1,
            "target": 9,
            "property": [
                {
                    "tf": "TRUE",
                    "dur": "85000",
                    "stamp": "1391450",
                    "date": "2/9/2014",
                    "time": "6:14:10 AM"
                }
            ]
        },
        {
            "source": 1,
            "target": 5,
            "property": [
                {
                    "tf": "TRUE",
                    "dur": "-1",
                    "stamp": "1391778",
                    "date": "2/7/2014",
                    "time": "9:02:58 AM"
                }
            ]
        },
        {
            "source": 1,
            "target": 4,
            "property": [
                {
                    "tf": "TRUE",
                    "dur": "53000",
                    "stamp": "1391868",
                    "date": "2/7/2014",
                    "time": "12:27:48 AM"
                }
            ]
        }
    ]
}